{
	"error": false,
	"version": "thirteen_plus",
	"filename": "PixelExperience_Plus_sagit-13.0-20230714-0951-UNOFFICIAL",
	"datetime": 1689327853,
	"size": 1525892364,
	"url": "https:\/\/down.warbler.cc\/XiaoMi-6\/PixelExperience\/13-Plus\/PixelExperience_Plus_sagit-13.0-20230714-0951-UNOFFICIAL.zip",
	"filehash": "8b240be9959f6d3daaf6fb6466a1a44faa4f1df6879c7bc03e3c4d5ba6d68347",
	"id": "8b240be9959f6d3daaf6fb6466a1a44faa4f1df6879c7bc03e3c4d5ba6d68347",
	"maintainers": [{
		"main_maintainer": false,
		"ci_username": "Nanhumly",
		"name": "Nanhumly"
	}],
	"donate_url": "https:\/\/bit.ly\/pixelexperiencedonate",
	"website_url": "https:\/\/download.pixelexperience.org",
	"news_url": "https:\/\/t.me\/PixelExperience",
	"forum_url": "https:\/\/t.me\/mi6indonesia"
}
